echocmdlib/__init__.py
echocmdlib/colors.py
echocmdlib/core.py
echocmdlib/loglib.py
echocmdlib/progress.py
echocmdlib/title.py
echocmdlib/ui.py
echocmdlib-0.1.7.dist-info/LICENSE.txt
echocmdlib-0.1.7.dist-info/METADATA
echocmdlib-0.1.7.dist-info/WHEEL
echocmdlib-0.1.7.dist-info/top_level.txt
echocmdlib-0.1.7.dist-info/RECORD
