Metadata-Version: 2.1
Name: echocmdlib
Version: 0.1.7
Home-page: https://github.com/codetimothy/echocmdlib
Author: Timothy Wu
Author-email: wuxiaoyu1107g@gmail.com
Classifier: Programming Language :: Python :: 3
Classifier: Operating System :: OS Independent
License-File: LICENSE.txt
Requires-Dist: colorama
Requires-Dist: pyfiglet
Requires-Dist: rich
